sentry_auth_ragtag/__init__.py
sentry_auth_ragtag/client.py
sentry_auth_ragtag/constants.py
sentry_auth_ragtag/provider.py
sentry_auth_ragtag/views.py
sentry_auth_ragtag/templates/sentry_auth_ragtag/configure.html
sentry_auth_ragtag-0.2.0.dist-info/METADATA
sentry_auth_ragtag-0.2.0.dist-info/RECORD
sentry_auth_ragtag-0.2.0.dist-info/WHEEL
sentry_auth_ragtag-0.2.0.dist-info/entry_points.txt
sentry_auth_ragtag-0.2.0.dist-info/top_level.txt
